{"title":"A New Start","markdown":{"yaml":{"title":"A New Start","author":"Hamish Dickson","date":"2023-01-04","categories":["news"]},"containsRefs":false,"markdown":"\n\nHi and thanks for getting this far!\n\nI'm excited to announce that after over 15 years of working in finance and then startups I have decided to become a freelancer!\n\nAs part of this I am (re)launching my blog. Most of my old posts have been converted to public notebooks on Kaggle, if you are interested please check them out.\n\nI hope here you will find interesting articles on what I'm working on, techniques I use a lot and hopefully a few demos. It will also act as a way for me to be more contactable... so please get in touch!\n\n![](thumbnail.jpg)\n\n"},"formats":{"html":{"execute":{"fig-width":7,"fig-height":5,"fig-format":"retina","fig-dpi":96,"df-print":"default","error":false,"eval":true,"cache":null,"freeze":true,"echo":true,"output":true,"warning":true,"include":true,"keep-md":false,"keep-ipynb":false,"ipynb":null,"enabled":null,"daemon":null,"daemon-restart":false,"debug":false,"ipynb-filters":[],"engine":"markdown"},"render":{"keep-tex":false,"keep-source":false,"keep-hidden":false,"prefer-html":false,"output-divs":true,"output-ext":"html","fig-align":"default","fig-pos":null,"fig-env":null,"code-fold":"none","code-overflow":"scroll","code-link":false,"code-line-numbers":false,"code-tools":false,"tbl-colwidths":"auto","merge-includes":true,"latex-auto-mk":true,"latex-auto-install":true,"latex-clean":true,"latex-max-runs":10,"latex-makeindex":"makeindex","latex-makeindex-opts":[],"latex-tlmgr-opts":[],"latex-input-paths":[],"latex-output-dir":null,"link-external-icon":false,"link-external-newwindow":false,"self-contained-math":false,"format-resources":[]},"pandoc":{"standalone":true,"wrap":"none","default-image-extension":"png","to":"html","css":["../../styles.css"],"output-file":"index.html"},"language":{},"metadata":{"lang":"en","fig-responsive":true,"quarto-version":"1.2.280","theme":"cosmo","title-block-banner":true,"title":"A New Start","author":"Hamish Dickson","date":"2023-01-04","categories":["news"]},"extensions":{"book":{"multiFile":true}}}}}